{"cameraMode":{"drawMode":0,"name":"Shaded","section":"Shading Mode"},"sceneLighting":true,"audioPlay":false,"sceneViewState":{"m_AlwaysRefresh":false,"showFog":true,"showSkybox":true,"showFlares":true,"showImageEffects":true,"showParticleSystems":true,"showVisualEffectGraphs":true,"m_FxEnabled":true},"in2DMode":false,"pivot":{"x":243.168212890625,"y":127.06878662109375,"z":-187.6434783935547},"rotation":{"x":-0.272426575422287,"y":-0.31380361318588259,"z":0.0945049524307251,"w":-0.9046627283096314},"size":14.585687637329102,"orthographic":false}